CongLingdaoYiShenruXuexiQukuaiLianMimaxue/README.md
CongLingdaoYiShenruXuexiQukuaiLianMimaxue/__init__.py
CongLingdaoYiShenruXuexiQukuaiLianMimaxue/__main__.py
CongLingdaoYiShenruXuexiQukuaiLianMimaxue/file.epub
CongLingdaoYiShenruXuexiQukuaiLianMimaxue/index.html
CongLingdaoYiShenruXuexiQukuaiLianMimaxue/css/__init__.py
CongLingdaoYiShenruXuexiQukuaiLianMimaxue/css/annotations.css
CongLingdaoYiShenruXuexiQukuaiLianMimaxue/css/main.css
CongLingdaoYiShenruXuexiQukuaiLianMimaxue/css/normalize.css
CongLingdaoYiShenruXuexiQukuaiLianMimaxue/css/popup.css
CongLingdaoYiShenruXuexiQukuaiLianMimaxue/font/__init__.py
CongLingdaoYiShenruXuexiQukuaiLianMimaxue/font/fontello.eot
CongLingdaoYiShenruXuexiQukuaiLianMimaxue/font/fontello.svg
CongLingdaoYiShenruXuexiQukuaiLianMimaxue/font/fontello.ttf
CongLingdaoYiShenruXuexiQukuaiLianMimaxue/font/fontello.woff
CongLingdaoYiShenruXuexiQukuaiLianMimaxue/img/__init__.py
CongLingdaoYiShenruXuexiQukuaiLianMimaxue/img/annotator-glyph-sprite.png
CongLingdaoYiShenruXuexiQukuaiLianMimaxue/img/annotator-icon-sprite.png
CongLingdaoYiShenruXuexiQukuaiLianMimaxue/img/apple-touch-icon.png
CongLingdaoYiShenruXuexiQukuaiLianMimaxue/img/cancelfullscreen.png
CongLingdaoYiShenruXuexiQukuaiLianMimaxue/img/close.png
CongLingdaoYiShenruXuexiQukuaiLianMimaxue/img/fullscreen.png
CongLingdaoYiShenruXuexiQukuaiLianMimaxue/img/loader.gif
CongLingdaoYiShenruXuexiQukuaiLianMimaxue/img/menu-icon.png
CongLingdaoYiShenruXuexiQukuaiLianMimaxue/img/save.png
CongLingdaoYiShenruXuexiQukuaiLianMimaxue/img/saved.png
CongLingdaoYiShenruXuexiQukuaiLianMimaxue/img/settings-s.png
CongLingdaoYiShenruXuexiQukuaiLianMimaxue/img/settings.png
CongLingdaoYiShenruXuexiQukuaiLianMimaxue/img/star.png
CongLingdaoYiShenruXuexiQukuaiLianMimaxue/js/__init__.py
CongLingdaoYiShenruXuexiQukuaiLianMimaxue/js/epub.js
CongLingdaoYiShenruXuexiQukuaiLianMimaxue/js/epub.min.js
CongLingdaoYiShenruXuexiQukuaiLianMimaxue/js/epub.min.map
CongLingdaoYiShenruXuexiQukuaiLianMimaxue/js/hooks.min.js
cong_lingdao_yi_shenru_xuexi_qukuai_lian_mimaxue-2024.3.5.0.dist-info/METADATA
cong_lingdao_yi_shenru_xuexi_qukuai_lian_mimaxue-2024.3.5.0.dist-info/WHEEL
cong_lingdao_yi_shenru_xuexi_qukuai_lian_mimaxue-2024.3.5.0.dist-info/entry_points.txt
cong_lingdao_yi_shenru_xuexi_qukuai_lian_mimaxue-2024.3.5.0.dist-info/top_level.txt
cong_lingdao_yi_shenru_xuexi_qukuai_lian_mimaxue-2024.3.5.0.dist-info/RECORD
